lion_linker/__init__.py
lion_linker/cli.py
lion_linker/core.py
lion_linker/lion_linker.py
lion_linker/retrievers.py
lion_linker/utils.py
lion_linker/prompt/__init__.py
lion_linker/prompt/examples.txt
lion_linker/prompt/generator.py
lion_linker/prompt/prompt_template_base.txt
lion_linker/prompt/prompt_template_detailed.txt
lion_linker/prompt/prompt_template_few_shot.txt
lion_linker/prompt/prompt_template_tablellama.txt
lion_linker-0.1.0.dist-info/licenses/LICENSE
lion_linker-0.1.0.dist-info/METADATA
lion_linker-0.1.0.dist-info/WHEEL
lion_linker-0.1.0.dist-info/entry_points.txt
lion_linker-0.1.0.dist-info/top_level.txt
lion_linker-0.1.0.dist-info/RECORD
