Metadata-Version: 2.4
Name: lion_linker
Version: 0.1.0
Summary: A package for entity linking using LionLinker.
Author-email: Roberto Avogadro <roberto.avogadro@sintef.no>
License: MIT
Project-URL: Homepage, https://github.com/roby-avo/lion_linker
Classifier: Programming Language :: Python :: 3
Classifier: License :: OSI Approved :: MIT License
Classifier: Operating System :: OS Independent
Requires-Python: >=3.10
License-File: LICENSE
Requires-Dist: pandas==2.2.3
Requires-Dist: requests==2.32.4
Requires-Dist: ollama==0.3.3
Requires-Dist: aiohttp==3.12.14
Requires-Dist: asyncio==3.4.3
Requires-Dist: tqdm==4.67.0
Requires-Dist: openai==1.54.4
Requires-Dist: python-dotenv==1.0.1
Requires-Dist: jsonargparse==4.37.0
Requires-Dist: torch>=2.8.0
Requires-Dist: transformers>=4.34.0
Provides-Extra: app
Requires-Dist: fastapi==0.115; extra == "app"
Requires-Dist: pydantic<3; extra == "app"
Requires-Dist: uvicorn==0.34; extra == "app"
Requires-Dist: pydantic-settings<3,>=2.0; extra == "app"
Requires-Dist: motor<4,>=3.5; extra == "app"
Provides-Extra: dev
Requires-Dist: flake8; extra == "dev"
Requires-Dist: black; extra == "dev"
Requires-Dist: isort; extra == "dev"
Requires-Dist: mypy; extra == "dev"
Requires-Dist: pre-commit; extra == "dev"
Provides-Extra: tablellama
Requires-Dist: transformers==4.34; extra == "tablellama"
Requires-Dist: tokenizers==0.14; extra == "tablellama"
Requires-Dist: protobuf==6.32.0; extra == "tablellama"
Requires-Dist: sentencepiece==0.2.1; extra == "tablellama"
Dynamic: license-file
